leica_scripts/__init__.py
leica_scripts/__main__.py
leica_scripts/core/LIF_metadata.py
leica_scripts/core/__init__.py
leica_scripts/core/_defaults.py
leica_scripts/core/coords_to_xml.py
leica_scripts/core/scripts_class.py
leica_scripts/gui/__init__.py
leica_scripts/gui/gui.py
leica_scripts-0.0.3.dist-info/licenses/LICENSE
leica_scripts-0.0.3.dist-info/METADATA
leica_scripts-0.0.3.dist-info/WHEEL
leica_scripts-0.0.3.dist-info/top_level.txt
leica_scripts-0.0.3.dist-info/RECORD
