Metadata-Version: 2.4
Name: leica_scripts
Version: 0.0.3
Summary: Leica Scripts
Author: RA Hoebe
License-Expression: GPL-3.0-or-later
Project-URL: Homepage, https://github.com/Cellular-Imaging-Amsterdam-UMC
Classifier: Programming Language :: Python :: 3
Classifier: Operating System :: OS Independent
Requires-Python: <3.13,>=3.12
License-File: LICENSE
Requires-Dist: cellpose==3.1.1.2
Requires-Dist: numpy>=2.0.2
Requires-Dist: pyshortcuts>=1.9.5
Requires-Dist: PyQt6>=6.9.0
Requires-Dist: lxml>=5.4.0
Requires-Dist: pyqtgraph>=0.13.7
Requires-Dist: superqt>=0.7.3
Requires-Dist: scikit-image>=0.25.2
Requires-Dist: pandas>=2.2.3
Dynamic: license-file
